pcnn/__init__.py
pcnn/data.py
pcnn/model.py
pcnn/module.py
pcnn/parameters.py
pcnn/util.py
pcnns-0.2.10.dist-info/METADATA
pcnns-0.2.10.dist-info/WHEEL
pcnns-0.2.10.dist-info/RECORD
