Metadata-Version: 2.3
Name: pcnns
Version: 0.2.10
Summary: 
Author: Loris Di Natale
Author-email: loris.dinatale@netplus.ch
Requires-Python: >=3.10,<4.0
Classifier: Programming Language :: Python :: 3
Classifier: Programming Language :: Python :: 3.10
Classifier: Programming Language :: Python :: 3.11
Classifier: Programming Language :: Python :: 3.12
Classifier: Programming Language :: Python :: 3.13
Requires-Dist: loguru (>=0.7.3,<0.8.0)
Requires-Dist: numpy (>=2.2.2,<3.0.0)
Requires-Dist: torch (>=2.6.0,<3.0.0)
